memon/__init__.py
memon/memon.py
memon-0.1.dist-info/DESCRIPTION.rst
memon-0.1.dist-info/METADATA
memon-0.1.dist-info/RECORD
memon-0.1.dist-info/WHEEL
memon-0.1.dist-info/metadata.json
memon-0.1.dist-info/top_level.txt
