Metadata-Version: 2.0
Name: memon
Version: 0.1
Summary: Simple Memory Monitor that helps to decide if it is time to dump data to disk.
Home-page: http://...
Author: TU Wien
Author-email: christoph.paulik@geo.tuwien.ac.at
License: BSD-3 Clause
Platform: UNKNOWN
Classifier: Development Status :: 4 - Beta
Classifier: Programming Language :: Python
Requires-Dist: psutil
